fairlearn/__init__.py
fairlearn/exceptions.py
fairlearn/show_versions.py
fairlearn/adversarial/__init__.py
fairlearn/adversarial/_adversarial_mitigation.py
fairlearn/adversarial/_backend_engine.py
fairlearn/adversarial/_constants.py
fairlearn/adversarial/_preprocessor.py
fairlearn/adversarial/_pytorch_engine.py
fairlearn/adversarial/_tensorflow_engine.py
fairlearn/datasets/__init__.py
fairlearn/datasets/_constants.py
fairlearn/datasets/_fetch_acs_income.py
fairlearn/datasets/_fetch_adult.py
fairlearn/datasets/_fetch_bank_marketing.py
fairlearn/datasets/_fetch_boston.py
fairlearn/datasets/_fetch_credit_card.py
fairlearn/datasets/_fetch_diabetes_hospital.py
fairlearn/experimental/__init__.py
fairlearn/experimental/enable_metric_frame_plotting.py
fairlearn/metrics/__init__.py
fairlearn/metrics/_annotated_metric_function.py
fairlearn/metrics/_base_metrics.py
fairlearn/metrics/_bootstrap.py
fairlearn/metrics/_disaggregated_result.py
fairlearn/metrics/_fairness_metrics.py
fairlearn/metrics/_generated_metrics.py
fairlearn/metrics/_group_feature.py
fairlearn/metrics/_make_derived_metric.py
fairlearn/metrics/_metric_frame.py
fairlearn/metrics/_plot_model_comparison.py
fairlearn/metrics/_plotter.py
fairlearn/postprocessing/__init__.py
fairlearn/postprocessing/_constants.py
fairlearn/postprocessing/_interpolated_thresholder.py
fairlearn/postprocessing/_plotting.py
fairlearn/postprocessing/_threshold_operation.py
fairlearn/postprocessing/_threshold_optimizer.py
fairlearn/postprocessing/_tradeoff_curve_utilities.py
fairlearn/preprocessing/__init__.py
fairlearn/preprocessing/_correlation_remover.py
fairlearn/reductions/__init__.py
fairlearn/reductions/_exponentiated_gradient/__init__.py
fairlearn/reductions/_exponentiated_gradient/_constants.py
fairlearn/reductions/_exponentiated_gradient/_lagrangian.py
fairlearn/reductions/_exponentiated_gradient/exponentiated_gradient.py
fairlearn/reductions/_grid_search/__init__.py
fairlearn/reductions/_grid_search/_grid_generator.py
fairlearn-0.10.0.dist-info/AUTHORS.md
fairlearn-0.10.0.dist-info/LICENSE
fairlearn-0.10.0.dist-info/METADATA
fairlearn-0.10.0.dist-info/WHEEL
fairlearn-0.10.0.dist-info/top_level.txt
fairlearn-0.10.0.dist-info/RECORD
