Metadata-Version: 2.1
Name: fairlearn
Version: 0.10.0
Summary: A Python package to assess and improve fairness of machine learning models.
Home-page: https://github.com/fairlearn/fairlearn
Author: Miroslav Dudik, Richard Edgar, Adrin Jalali, Roman Lutz, Michael Madaio, Hilde Weerts, Allie Saizan
Author-email: fairlearn-internal@python.org
Classifier: Programming Language :: Python :: 3.8
Classifier: Programming Language :: Python :: 3.9
Classifier: Programming Language :: Python :: 3.10
Classifier: Programming Language :: Python :: 3.11
Classifier: License :: OSI Approved :: MIT License
Classifier: Operating System :: OS Independent
Classifier: Development Status :: 3 - Alpha
Requires-Python: >=3.8
License-File: LICENSE
License-File: AUTHORS.md
Requires-Dist: numpy>=1.24.4
Requires-Dist: pandas>=2.0.3
Requires-Dist: scikit-learn>=1.2.1
Requires-Dist: scipy>=1.9.3
